astakosa/__init__.py
astakosa/file.py
astakosa-0.1.7.dist-info/METADATA
astakosa-0.1.7.dist-info/WHEEL
astakosa-0.1.7.dist-info/top_level.txt
astakosa-0.1.7.dist-info/RECORD
